CHANGELOG
MANIFEST.in
README.md
VERSION
setup.py
anodyne/__init__.py
anodyne/connections.py
anodyne/data.py
anodyne/engines.py
anodyne/exceptions.py
anodyne.egg-info/PKG-INFO
anodyne.egg-info/SOURCES.txt
anodyne.egg-info/dependency_links.txt
anodyne.egg-info/requires.txt
anodyne.egg-info/top_level.txt
requirements/core.txt
requirements/test.txt