Metadata-Version: 1.1
Name: anodyne
Version: 1.0.1
Summary: SQLAlchemy Database Utilities
Home-page: https://github.com/amilstead/anodyne
Author: Alex Milstead
Author-email: alex@amilstead.com
License: UNKNOWN
Keywords: sqlalchemy
Platform: UNKNOWN
Classifier: Development Status :: 3 - Alpha
Classifier: Intended Audience :: Developers
Classifier: Natural Language :: English
Classifier: Programming Language :: Python
Classifier: Topic :: Database 
Classifier: License :: OSI Approved :: GNU General Public License (GPL)
